aeshandler/__init__.py
aeshandler/aeshandler.py
aeshandler-0.3.dist-info/METADATA
aeshandler-0.3.dist-info/WHEEL
aeshandler-0.3.dist-info/top_level.txt
aeshandler-0.3.dist-info/RECORD
